README.md
setup.py
install_requires/__init__.py
install_requires/core.py
install_requires.egg-info/PKG-INFO
install_requires.egg-info/SOURCES.txt
install_requires.egg-info/dependency_links.txt
install_requires.egg-info/requires.txt
install_requires.egg-info/top_level.txt