Metadata-Version: 2.1
Name: install-requires
Version: 0.2.0
Summary: Convert requirements between formats
Home-page: https://github.com/orsinium/install-requires
Author: orsinium
License: UNKNOWN
Platform: UNKNOWN
Provides-Extra: poetry
Provides-Extra: pipfile
